spaceandtime/__init__.py
spaceandtime/__main__.py
spaceandtime/apiversions.json
spaceandtime/spaceandtime.py
spaceandtime/sxtbaseapi.py
spaceandtime/sxtbiscuits.py
spaceandtime/sxtenums.py
spaceandtime/sxtexceptions.py
spaceandtime/sxtkeymanager.py
spaceandtime/sxtresource.py
spaceandtime/sxtuser.py
spaceandtime-1.1.73.dist-info/licenses/LICENSE
spaceandtime-1.1.73.dist-info/METADATA
spaceandtime-1.1.73.dist-info/WHEEL
spaceandtime-1.1.73.dist-info/entry_points.txt
spaceandtime-1.1.73.dist-info/top_level.txt
spaceandtime-1.1.73.dist-info/RECORD
