Metadata-Version: 2.4
Name: spaceandtime
Version: 1.1.73
Summary: SDK for Space and Time verifiable database
Author-email: Stephen Hilton <stephen@spaceandtime.io>
License: MIT License
Project-URL: Homepage, https://spaceandtime.io
Project-URL: Docs, https://docs.spaceandtime.io
Project-URL: Documentation, https://docs.spaceandtime.io
Project-URL: Github, https://github.com/spaceandtimelabs/SxT-Python-SDK
Keywords: space and time,sxt,spaceandtime,verifiable,database,web3,blockchain,data warehouse,data
Classifier: License :: OSI Approved :: MIT License
Classifier: Programming Language :: Python
Classifier: Programming Language :: Python :: 3
Requires-Python: >=3.10
License-File: LICENSE
Requires-Dist: PyNaCl==1.5.0
Requires-Dist: python-dotenv==1.0.0
Requires-Dist: Requests==2.31.0
Requires-Dist: pandas>=2.1.3
Requires-Dist: pyarrow>=14.0.1
Requires-Dist: fastparquet>=2023.10.1
Requires-Dist: biscuit-python>=0.2.0
Provides-Extra: dev
Requires-Dist: pip-tools; extra == "dev"
Requires-Dist: pytest; extra == "dev"
Dynamic: license-file
